lab_ml/__init__.py
lab_ml/main.py
lab_ml5sem-1.0.3.dist-info/METADATA
lab_ml5sem-1.0.3.dist-info/WHEEL
lab_ml5sem-1.0.3.dist-info/top_level.txt
lab_ml5sem-1.0.3.dist-info/RECORD
