Metadata-Version: 2.1
Name: lab-ml5sem
Version: 1.0.3
Summary: A package for data visualization and machine learning helper functions.
Home-page: https://github.com/Rohitlyengar/lab_ml
Author: Rohit Iyengar
Author-email: rohitiyengar8@gmail.com
License: MIT
Project-URL: Source, https://github.com/Rohitlyengar/lab_ml
Project-URL: Bug Tracker, https://github.com/Rohitlyengar/lab_ml/issues
Keywords: machine-learning data-visualization helpers
Classifier: Development Status :: 3 - Alpha
Classifier: Programming Language :: Python :: 3
Classifier: Programming Language :: Python :: 3.7
Classifier: Programming Language :: Python :: 3.8
Classifier: Programming Language :: Python :: 3.9
Classifier: Programming Language :: Python :: 3.10
Classifier: Programming Language :: Python :: 3.11
Classifier: License :: OSI Approved :: MIT License
Classifier: Operating System :: OS Independent
Classifier: Topic :: Scientific/Engineering :: Visualization
Classifier: Topic :: Software Development :: Libraries :: Python Modules
Requires-Python: >=3.7
Requires-Dist: scikit-learn
Requires-Dist: seaborn
Requires-Dist: numpy
Requires-Dist: matplotlib
